{"airport":{"id":"DC3Rf32mQq","IATA":"JMK","name":"Mykonos Island National Airport","location":{"latitude":37.434812790882354,"longitude":25.347115947082557,"description":"Delos, Mykonos, Greece","radius":174,"city":"Mikonos","countryCode":"GR","countryName":"Greece"},"timeZone":"Europe/Athens","imageURL":"https://images.loungebuddy.com/loungebuddy/image/upload/v1478119612/diveug9cy4k9sbzr9uxj.jpg"},"meta":{"description":"Buy airport lounge access. Learn how to access Mykonos Island National Airport (JMK) lounges with a day pass, airline status, membership, or credit card.","hasNonBookableLounges":false,"hasBookableLougnes":true,"mapkitToken":"eyJhbGciOiJFUzI1NiIsInR5cCI6IkpXVCIsImtpZCI6IkYyTUE4U0RBVkMifQ.eyJpc3MiOiI1UUg4Wk00OUxRIiwiaWF0IjoxNzMzMDk3NjAwLCJleHAiOjE3MzM3MDI0MDAsIm9yaWdpbiI6Imh0dHBzOi8vbmV4dC5sb3VuZ2VidWRkeS5jb20ifQ.D7_q8p1VCvTVu7AthoqHYlbQ6ejjvaGTJUt1tE3lqJF3btpyFWm-tOLAjGK1rrv4EbT1CnO3YsPHwxH0gW0dQg"},"lounges":[{"id":"PIJHDgy5Du","name":"Your Mykonian Luxury Lounge by Goldair Handling","terminal":"Main Terminal","location":{"latitude":null,"longitude":null,"terminalDirections":"Located landside in the Intra-Schengen Area, on the 1st Floor before passport control."},"airside":"insideSecurity","loungeImage":"https://images.loungebuddy.com/loungebuddy/image/upload/t_keyart_mobile/v1459215296/1714065105666.jpg","hours":[[800,2000],[800,2000],[800,2000],[800,2000],[800,2000],[800,2000],[800,2000]],"amenities":[{"id":"SNACKS","name":"Snacks","paid":false},{"id":"SPIRITS_LIQUOR","name":"Spirits & Liquor","paid":false},{"id":"BEER_WINE","name":"Beer & Wine","paid":false},{"id":"WIFI","name":"Wi-Fi","paid":false},{"id":"FLIGHT_MONITORS","name":"Flight Monitors","paid":false},{"id":"NEWSPAPERS","name":"Newspapers & Magazines","paid":false},{"id":"TV","name":"TVs","paid":false},{"id":"INTERNET_TERMINALS","name":"Internet Terminals","paid":false},{"id":"NON-SMOKING","name":"Non-Smoking","paid":false}],"amenityGroups":"Food · Drinks","accessType":"PURCHASABLE","tempClosed":"open","slugPath":"your-mykonian-luxury-lounge-by-goldair-handling-main-terminal-PIJHDgy5Du","price":{"currency":"EUR","price":30},"airport":{"id":"DC3Rf32mQq","IATA":"JMK","name":"Mykonos Island National Airport","location":{"latitude":37.434812790882354,"longitude":25.347115947082557,"description":"Delos, Mykonos, Greece","radius":174,"city":"Mikonos","countryCode":"GR","countryName":"Greece"},"timeZone":"Europe/Athens","imageURL":"https://images.loungebuddy.com/loungebuddy/image/upload/v1478119612/diveug9cy4k9sbzr9uxj.jpg"},"images":["https://images.loungebuddy.com/loungebuddy/image/upload/t_keyart_mobile/v1459215296/1714065105666.jpg","https://images.loungebuddy.com/loungebuddy/image/upload/t_keyart_mobile/v1459215296/1714065105657.jpg"]}]}