{"status":200,"meta":{"description":"Sala VIP Cap Des Falco at Ibiza Airport (IBZ), Main Terminal. Learn more about the lounge: amenities, photos, review, opening hours, location."},"lounge":{"id":"4FpkxHCfm9","name":"Sala VIP Cap Des Falco","terminal":"Main Terminal","location":{"latitude":null,"longitude":null,"terminalDirections":"Located on the 1st Floor, next to Gate 1."},"airside":"insideSecurity","loungeImage":"https://images.loungebuddy.com/loungebuddy/image/upload/t_keyart_mobile/v1459215296/f8m7njmvpqgfox1pwqzc.jpg","hours":[[545,0],[545,0],[545,0],[545,0],[545,0],[545,0],[545,0]],"amenities":[{"id":"SNACKS","name":"Snacks","paid":false},{"id":"SPIRITS_LIQUOR","name":"Spirits & Liquor","paid":false},{"id":"BEER_WINE","name":"Beer & Wine","paid":false},{"id":"WIFI","name":"Wi-Fi","paid":false},{"id":"FLIGHT_MONITORS","name":"Flight Monitors","paid":false},{"id":"NEWSPAPERS","name":"Newspapers & Magazines","paid":false},{"id":"TV","name":"TVs","paid":false},{"id":"INTERNET_TERMINALS","name":"Internet Terminals","paid":false},{"id":"NON-SMOKING","name":"Non-Smoking","paid":false},{"id":"18_CARDHOLDER","name":"18+ Cardholder","paid":false}],"amenityGroups":null,"accessType":"WALKINS_ACCEPTED","tempClosed":"open","slugPath":"sala-vip-cap-des-falco-main-terminal-4FpkxHCfm9","price":{"price":38,"currency":"EUR"},"airport":{"id":"jZ6nhbCm3j","IATA":"IBZ","name":"Ibiza Airport","location":{"latitude":38.876255,"longitude":1.367908,"description":"Ibiza, Spain","radius":120,"city":"Ibiza","countryCode":"ES","countryName":"Spain"},"timeZone":"Europe/Madrid","imageURL":"https://images.loungebuddy.com/loungebuddy/image/upload/v1478119625/o0u1cbpf3ilg8widqgnx.jpg"},"images":["https://images.loungebuddy.com/loungebuddy/image/upload/t_keyart_mobile/v1459215296/f8m7njmvpqgfox1pwqzc.jpg"],"description":"","purchasable":false,"importantInformation":{"general":["Children 5 years old and under are admitted free with an adult."],"warning":[],"regulatory":["Open 6:00 AM - 12:30 AM from April to October and 6:15 AM - 10:45 PM from November to March."],"hasContent":true},"fullImages":["https://images.loungebuddy.com/loungebuddy/image/upload/c_fit,h_2000,w_2000/f8m7njmvpqgfox1pwqzc.jpg","https://images.loungebuddy.com/loungebuddy/image/upload/c_fit,h_2000,w_2000/grvvs3lgectboplkckaa.jpg","https://images.loungebuddy.com/loungebuddy/image/upload/c_fit,h_2000,w_2000/qybvhxyupzwktnzakqte.jpg","https://images.loungebuddy.com/loungebuddy/image/upload/c_fit,h_2000,w_2000/uly3duzmv54jfd7uhmx0.jpg","https://images.loungebuddy.com/loungebuddy/image/upload/c_fit,h_2000,w_2000/p26u30zzptht3f7yknun.jpg","https://images.loungebuddy.com/loungebuddy/image/upload/c_fit,h_2000,w_2000/yhquslhgiipzpeacir5z.jpg","https://images.loungebuddy.com/loungebuddy/image/upload/c_fit,h_2000,w_2000/facjwe27lpftbsluiwga.jpg","https://images.loungebuddy.com/loungebuddy/image/upload/c_fit,h_2000,w_2000/weem4skhan0jrzcgidtn.jpg","https://images.loungebuddy.com/loungebuddy/image/upload/c_fit,h_2000,w_2000/tzxgiej0dmtbru1umpzr.jpg","https://images.loungebuddy.com/loungebuddy/image/upload/c_fit,h_2000,w_2000/zdc7nrglvqkgcexjgzo7.jpg","https://images.loungebuddy.com/loungebuddy/image/upload/c_fit,h_2000,w_2000/zt7zadxuwntm76ehzvtc.jpg","https://images.loungebuddy.com/loungebuddy/image/upload/c_fit,h_2000,w_2000/z1q5lhex2izcnhh3dfh6.jpg"],"bookingLoungeId":null},"allAmenities":[{"id":"PREMIUM_FOOD_FREE","name":"Premium Food","paid":false,"icons":{"size24":"https://images.loungebuddy.com/loungebuddy/image/upload/v1590181336/amenities/PREMIUM_FOOD.png"}},{"id":"PREMIUM_FOOD","name":"Premium Food","paid":true,"icons":{"size24":"https://images.loungebuddy.com/loungebuddy/image/upload/v1590181336/amenities/PREMIUM_FOOD.png"}},{"id":"SNACKS_FREE","name":"Snacks","paid":false,"icons":{"size24":"https://images.loungebuddy.com/loungebuddy/image/upload/v1590181336/amenities/SNACKS_FREE.png"}},{"id":"SPIRITS_LIQUOR_FREE","name":"Spirits & Liquor","paid":false,"icons":{"size24":"https://images.loungebuddy.com/loungebuddy/image/upload/v1590181336/amenities/SPIRITS_LIQUOR.png"}},{"id":"SPIRITS_LIQUOR","name":"Spirits & Liquor","paid":true,"icons":{"size24":"https://images.loungebuddy.com/loungebuddy/image/upload/v1590181336/amenities/SPIRITS_LIQUOR.png"}},{"id":"BEER_WINE_FREE","name":"Beer & Wine","paid":false,"icons":{"size24":"https://images.loungebuddy.com/loungebuddy/image/upload/v1590181336/amenities/BEER_WINE.png"}},{"id":"BEER_WINE","name":"Beer & Wine","paid":true,"icons":{"size24":"https://images.loungebuddy.com/loungebuddy/image/upload/v1590181336/amenities/BEER_WINE.png"}},{"id":"WIFI_FREE","name":"Wi-Fi","paid":false,"icons":{"size24":"https://images.loungebuddy.com/loungebuddy/image/upload/v1590181336/amenities/WIFI.png"}},{"id":"WIFI","name":"Wi-Fi","paid":true,"icons":{"size24":"https://images.loungebuddy.com/loungebuddy/image/upload/v1590181336/amenities/WIFI.png"}},{"id":"SHOWERS_FREE","name":"Showers","paid":false,"icons":{"size24":"https://images.loungebuddy.com/loungebuddy/image/upload/v1590181336/amenities/SHOWERS.png"}},{"id":"SHOWERS","name":"Showers","paid":true,"icons":{"size24":"https://images.loungebuddy.com/loungebuddy/image/upload/v1590181336/amenities/SHOWERS.png"}},{"id":"SPA_FREE","name":"Spa Services","paid":false,"icons":{"size24":"https://images.loungebuddy.com/loungebuddy/image/upload/v1590181336/amenities/SPA.png"}},{"id":"SPA","name":"Spa Services","paid":true,"icons":{"size24":"https://images.loungebuddy.com/loungebuddy/image/upload/v1590181336/amenities/SPA.png"}},{"id":"FLIGHT_MONITORS","name":"Flight Monitors","paid":false,"icons":{"size24":"https://images.loungebuddy.com/loungebuddy/image/upload/v1590181336/amenities/FLIGHT_MONITORS.png"}},{"id":"NEWSPAPERS","name":"Newspapers & Magazines","paid":false,"icons":{"size24":"https://images.loungebuddy.com/loungebuddy/image/upload/v1590181336/amenities/NEWSPAPERS.png"}},{"id":"TV","name":"TVs","paid":false,"icons":{"size24":"https://images.loungebuddy.com/loungebuddy/image/upload/v1590181336/amenities/TV.png"}},{"id":"PRIVATE_ROOMS_FREE","name":"Private Rooms","paid":false,"icons":{"size24":"https://images.loungebuddy.com/loungebuddy/image/upload/v1590181336/amenities/PRIVATE_ROOMS.png"}},{"id":"PRIVATE_ROOMS","name":"Private Rooms","paid":true,"icons":{"size24":"https://images.loungebuddy.com/loungebuddy/image/upload/v1590181336/amenities/PRIVATE_ROOMS.png"}},{"id":"CHILDREN_ROOMS","name":"Children's Area","paid":false,"icons":{"size24":"https://images.loungebuddy.com/loungebuddy/image/upload/v1590181336/amenities/CHILDREN_ROOMS.png"}},{"id":"CONFERENCE_ROOMS_FREE","name":"Conference Rooms","paid":false,"icons":{"size24":"https://images.loungebuddy.com/loungebuddy/image/upload/v1590181336/amenities/CONFERENCE_ROOMS.png"}},{"id":"CONFERENCE_ROOMS","name":"Conference Rooms","paid":true,"icons":{"size24":"https://images.loungebuddy.com/loungebuddy/image/upload/v1590181336/amenities/CONFERENCE_ROOMS.png"}},{"id":"INTERNET_TERMINALS","name":"Internet Terminals","paid":false,"icons":{"size24":"https://images.loungebuddy.com/loungebuddy/image/upload/v1590181336/amenities/INTERNET_TERMINALS.png"}},{"id":"PRINTERS_FREE","name":"Printers & Copiers","paid":false,"icons":{"size24":"https://images.loungebuddy.com/loungebuddy/image/upload/v1590181336/amenities/PRINTERS.png"}},{"id":"PRINTERS","name":"Printers & Copiers","paid":true,"icons":{"size24":"https://images.loungebuddy.com/loungebuddy/image/upload/v1590181336/amenities/PRINTERS.png"}},{"id":"TELEPHONES","name":"Telephones","paid":false,"icons":{"size24":"https://images.loungebuddy.com/loungebuddy/image/upload/v1590181336/amenities/TELEPHONES.png"}},{"id":"SMOKING_ROOMS","name":"Smoking Area","paid":false,"icons":{"size24":"https://images.loungebuddy.com/loungebuddy/image/upload/v1590181336/amenities/SMOKING_ROOMS.png"}},{"id":"NON-SMOKING","name":"Non-Smoking","paid":false,"icons":{"size24":"https://images.loungebuddy.com/loungebuddy/image/upload/v1590181336/amenities/NON-SMOKING.png"}},{"id":"SHOE_SHINE","name":"Shoe Shine","paid":false,"icons":{"size24":"https://images.loungebuddy.com/loungebuddy/image/upload/v1590181336/amenities/SHOE_SHINE.png"}},{"id":"18_CARDHOLDER","name":"18+ Cardholder","paid":false,"icons":{"size24":"https://images.loungebuddy.com/loungebuddy/image/upload/v1590181336/amenities/18_CARDHOLDER.png"}},{"id":"21_CARDHOLDER","name":"21+ Cardholder","paid":false,"icons":{"size24":"https://images.loungebuddy.com/loungebuddy/image/upload/v1590181336/amenities/21_CARDHOLDER.png"}},{"id":"GYM","name":"Gym","paid":true,"icons":{"size24":"https://images.loungebuddy.com/loungebuddy/image/upload/v1590181336/amenities/GYM.png"}},{"id":"GYM_FREE","name":"Gym","paid":false,"icons":{"size24":"https://images.loungebuddy.com/loungebuddy/image/upload/v1590181336/amenities/GYM.png"}},{"id":"CLOTHES_PRESS_FREE","name":"Clothes Press","paid":false,"icons":{"size24":"https://images.loungebuddy.com/loungebuddy/image/upload/v1590181336/amenities/CLOTHES_PRESS_FREE.png"}}],"reviews":[{"createdAt":"2019-10-01T12:23:59.371Z","visibilityRating":14.416666666666666,"rating":1,"member":{"profileIcon":"/images/lounges/avatar_2x_ij4mbe.png","name":"Yulia","objectId":"AMaPr1HFzx"},"type":{"parent":"4FpkxHCfm9","name":"review"},"content":"The lounge doesn’t let people in before 4 hours from the flight departure time. I’d even be happy to pay extra for an extra hour, silly rule. Normally lounges are not this uptight.","parentId":"4FpkxHCfm9"},{"createdAt":"2019-09-02T13:10:54.101Z","visibilityRating":14.75,"rating":1,"member":{"profileIcon":"/images/lounges/avatar_2x_ij4mbe.png","name":"Zack","objectId":"WqWCwyeSnq"},"type":{"parent":"4FpkxHCfm9","name":"review"},"content":"Too small for the size of the airport.","parentId":"4FpkxHCfm9"},{"createdAt":"2019-05-29T19:52:00.311Z","visibilityRating":15.833333333333334,"rating":1,"member":{"profileIcon":"/images/lounges/avatar_2x_ij4mbe.png","name":"Jan ","objectId":"Nr8pp8ijLR"},"type":{"parent":"4FpkxHCfm9","name":"review"},"content":"At first we were rebuffed as the lounge was declared full, even though at most half the chairs were taken. Only after another rebuffed guest made a point of asking for the manager were we allowed in.","parentId":"4FpkxHCfm9"},{"createdAt":"2019-03-18T20:34:19.770Z","visibilityRating":16.75,"rating":2,"member":{"profileIcon":"/images/lounges/avatar_2x_ij4mbe.png","name":"funtobejulie","objectId":"75BDAcAJrP"},"type":{"parent":"4FpkxHCfm9","name":"review"},"content":"Not terrible. Very empty during the winter months. Hot food had been sitting out for a loooooong time.","parentId":"4FpkxHCfm9"},{"createdAt":"2018-10-03T09:27:13.622Z","visibilityRating":18.75,"rating":1,"member":{"profileIcon":"/images/lounges/avatar_2x_ij4mbe.png","name":"David","objectId":"XgADVpnCNd"},"type":{"parent":"4FpkxHCfm9","name":"review"},"content":"One of the worst lounges I have ever seen. Really bad service - no refill or cleanup. Totally unfriendly service. Save your money and do not came here.","parentId":"4FpkxHCfm9"},{"createdAt":"2018-09-14T02:22:10.954Z","visibilityRating":18.916666666666668,"rating":2,"member":{"profileIcon":"/images/lounges/avatar_2x_ij4mbe.png","name":"Anonymous","objectId":"BReDhV50bt"},"type":{"parent":"4FpkxHCfm9","name":"review"},"content":"Entered the lounge while it was not busy but there were empty plates everywhere and it was far from clean. If you need a power outlet there is a bar table to charge, but no outlets next to the seats.","parentId":"4FpkxHCfm9"},{"createdAt":"2018-04-01T14:28:47.638Z","visibilityRating":20.916666666666668,"rating":4,"member":{"profileIcon":"/images/lounges/avatar_2x_ij4mbe.png","name":"Chiara","objectId":"KW1NvKuA8m"},"type":{"parent":"4FpkxHCfm9","name":"review"},"content":"Beautiful and clean. Nespresso coffee, tea water, still and soarkling fruit juices, sandwich, finger food, salads, fruits.","parentId":"4FpkxHCfm9"},{"createdAt":"2017-06-06T19:58:15.759Z","visibilityRating":24.5,"rating":4,"member":{"profileIcon":"/images/lounges/avatar_2x_ij4mbe.png","name":"Sam Maes","objectId":"G3jxsYH2ex"},"type":{"parent":"4FpkxHCfm9","name":"review"},"content":"This lounge is small but cute and has everything you need. Wide variety of drinks, Nespresso coffee and food. The food was pre-packed but there were salads, sandwiches and a lot of fresh fruit.","parentId":"4FpkxHCfm9"},{"createdAt":"2017-05-16T17:42:12.645Z","visibilityRating":24.75,"rating":3,"member":{"profileIcon":"/images/lounges/avatar_2x_ij4mbe.png","name":"Andrei","objectId":"rdl3Dhccad"},"type":{"parent":"4FpkxHCfm9","name":"review"},"content":"To add to the previous feedback, I've entered with a Priority Pass card, so it's accepted (and advertised) as of May 2017. Very bright and clean. Only one staff but very friendly and helpful.","parentId":"4FpkxHCfm9"},{"createdAt":"2016-09-17T09:16:46.022Z","visibilityRating":27.583333333333332,"rating":1,"member":{"profileIcon":"/images/lounges/avatar_2x_ij4mbe.png","name":"Anonymous","objectId":"RvCzbWnCM8"},"type":{"parent":"4FpkxHCfm9","name":"review"},"content":"This lounge is NOT accessible with Priority Pass. I was denied access on September 17, 2016. They said that they opened with a new company in June and are no longer working with Priority Pass.","parentId":"4FpkxHCfm9"}],"otherLounges":[],"capacity":null,"googleMapKey":"AIzaSyDaxxnWYwWefsgNxrzdkvEEexN5m7NSVew"}