{"status":200,"meta":{"description":"ITA Airways Piazza di Spagna at Leonardo da Vinci-Fiumicino Airport (FCO), Terminal 3, E-Gates. Learn more about the lounge: amenities, photos, review, opening hours, location."},"lounge":{"id":"6iypTOVK9Y","name":"ITA Airways Piazza di Spagna","terminal":"Terminal 3, E-Gates","location":{"latitude":null,"longitude":null,"terminalDirections":"Boarding Area E - Non-Schengen, near Gate E11"},"airside":"insideSecurity","loungeImage":"https://images.loungebuddy.com/loungebuddy/image/upload/t_keyart_mobile/v1459215296/hyijp0ry30yf6anubb66.jpg","hours":[[-1,"First Departure-Last Departure"],[-1,"First Departure-Last Departure"],[-1,"First Departure-Last Departure"],[-1,"First Departure-Last Departure"],[-1,"First Departure-Last Departure"],[-1,"First Departure-Last Departure"],[-1,"First Departure-Last Departure"]],"amenities":[{"id":"PREMIUM_FOOD","name":"Premium Food","paid":false},{"id":"SNACKS","name":"Snacks","paid":false},{"id":"SPIRITS_LIQUOR","name":"Spirits & Liquor","paid":false},{"id":"BEER_WINE","name":"Beer & Wine","paid":false},{"id":"WIFI","name":"Wi-Fi","paid":false},{"id":"SHOWERS","name":"Showers","paid":false},{"id":"FLIGHT_MONITORS","name":"Flight Monitors","paid":false},{"id":"NEWSPAPERS","name":"Newspapers & Magazines","paid":false},{"id":"TV","name":"TVs","paid":false},{"id":"PRINTERS","name":"Printers & Copiers","paid":false},{"id":"NON-SMOKING","name":"Non-Smoking","paid":false},{"id":"18_CARDHOLDER","name":"18+ Cardholder","paid":false}],"amenityGroups":null,"accessType":"NO_ACCESS","tempClosed":"open","slugPath":"ita-airways-piazza-di-spagna-terminal-3-e-gates-6iypTOVK9Y","price":null,"airport":{"id":"Tb3G9hmCc1","IATA":"FCO","name":"Leonardo da Vinci-Fiumicino Airport","location":{"latitude":41.798448,"longitude":12.248676,"description":"Fiumicino, Rome, Italy","radius":1500,"city":"Rome","countryCode":"IT","countryName":"Italy"},"timeZone":"Europe/Rome","imageURL":"https://images.loungebuddy.com/loungebuddy/image/upload/v1478119618/bgvsjwslohzimhsilewg.jpg"},"images":["https://images.loungebuddy.com/loungebuddy/image/upload/t_keyart_mobile/v1459215296/hyijp0ry30yf6anubb66.jpg"],"description":"","purchasable":false,"importantInformation":{"general":[],"warning":[],"regulatory":[],"hasContent":false},"fullImages":["https://images.loungebuddy.com/loungebuddy/image/upload/c_fit,h_2000,w_2000/hyijp0ry30yf6anubb66.jpg","https://images.loungebuddy.com/loungebuddy/image/upload/c_fit,h_2000,w_2000/lmqfnycdzwuwqbup5n8w.jpg","https://images.loungebuddy.com/loungebuddy/image/upload/c_fit,h_2000,w_2000/ktaxpjzg7jitfrv2etir.jpg","https://images.loungebuddy.com/loungebuddy/image/upload/c_fit,h_2000,w_2000/dm5b4zvobikgvtzu4dx3.jpg","https://images.loungebuddy.com/loungebuddy/image/upload/c_fit,h_2000,w_2000/oigctlu5wmhgmhmyz9ym.jpg","https://images.loungebuddy.com/loungebuddy/image/upload/c_fit,h_2000,w_2000/aldpvd8xk0mnssbdiy7n.jpg","https://images.loungebuddy.com/loungebuddy/image/upload/c_fit,h_2000,w_2000/kl94k2re86fyd7wmxb4j.jpg","https://images.loungebuddy.com/loungebuddy/image/upload/c_fit,h_2000,w_2000/tqahfwttpakiywg8pc75.jpg","https://images.loungebuddy.com/loungebuddy/image/upload/c_fit,h_2000,w_2000/smmpocz2lxahwfheaafe.jpg","https://images.loungebuddy.com/loungebuddy/image/upload/c_fit,h_2000,w_2000/vi8yphnq1xol0kelhnbf.jpg","https://images.loungebuddy.com/loungebuddy/image/upload/c_fit,h_2000,w_2000/ymfccnxolhna2ywcg14y.jpg"],"bookingLoungeId":null},"allAmenities":[{"id":"PREMIUM_FOOD_FREE","name":"Premium Food","paid":false,"icons":{"size24":"https://images.loungebuddy.com/loungebuddy/image/upload/v1590181336/amenities/PREMIUM_FOOD.png"}},{"id":"PREMIUM_FOOD","name":"Premium Food","paid":true,"icons":{"size24":"https://images.loungebuddy.com/loungebuddy/image/upload/v1590181336/amenities/PREMIUM_FOOD.png"}},{"id":"SNACKS_FREE","name":"Snacks","paid":false,"icons":{"size24":"https://images.loungebuddy.com/loungebuddy/image/upload/v1590181336/amenities/SNACKS_FREE.png"}},{"id":"SPIRITS_LIQUOR_FREE","name":"Spirits & Liquor","paid":false,"icons":{"size24":"https://images.loungebuddy.com/loungebuddy/image/upload/v1590181336/amenities/SPIRITS_LIQUOR.png"}},{"id":"SPIRITS_LIQUOR","name":"Spirits & Liquor","paid":true,"icons":{"size24":"https://images.loungebuddy.com/loungebuddy/image/upload/v1590181336/amenities/SPIRITS_LIQUOR.png"}},{"id":"BEER_WINE_FREE","name":"Beer & Wine","paid":false,"icons":{"size24":"https://images.loungebuddy.com/loungebuddy/image/upload/v1590181336/amenities/BEER_WINE.png"}},{"id":"BEER_WINE","name":"Beer & Wine","paid":true,"icons":{"size24":"https://images.loungebuddy.com/loungebuddy/image/upload/v1590181336/amenities/BEER_WINE.png"}},{"id":"WIFI_FREE","name":"Wi-Fi","paid":false,"icons":{"size24":"https://images.loungebuddy.com/loungebuddy/image/upload/v1590181336/amenities/WIFI.png"}},{"id":"WIFI","name":"Wi-Fi","paid":true,"icons":{"size24":"https://images.loungebuddy.com/loungebuddy/image/upload/v1590181336/amenities/WIFI.png"}},{"id":"SHOWERS_FREE","name":"Showers","paid":false,"icons":{"size24":"https://images.loungebuddy.com/loungebuddy/image/upload/v1590181336/amenities/SHOWERS.png"}},{"id":"SHOWERS","name":"Showers","paid":true,"icons":{"size24":"https://images.loungebuddy.com/loungebuddy/image/upload/v1590181336/amenities/SHOWERS.png"}},{"id":"SPA_FREE","name":"Spa Services","paid":false,"icons":{"size24":"https://images.loungebuddy.com/loungebuddy/image/upload/v1590181336/amenities/SPA.png"}},{"id":"SPA","name":"Spa Services","paid":true,"icons":{"size24":"https://images.loungebuddy.com/loungebuddy/image/upload/v1590181336/amenities/SPA.png"}},{"id":"FLIGHT_MONITORS","name":"Flight Monitors","paid":false,"icons":{"size24":"https://images.loungebuddy.com/loungebuddy/image/upload/v1590181336/amenities/FLIGHT_MONITORS.png"}},{"id":"NEWSPAPERS","name":"Newspapers & Magazines","paid":false,"icons":{"size24":"https://images.loungebuddy.com/loungebuddy/image/upload/v1590181336/amenities/NEWSPAPERS.png"}},{"id":"TV","name":"TVs","paid":false,"icons":{"size24":"https://images.loungebuddy.com/loungebuddy/image/upload/v1590181336/amenities/TV.png"}},{"id":"PRIVATE_ROOMS_FREE","name":"Private Rooms","paid":false,"icons":{"size24":"https://images.loungebuddy.com/loungebuddy/image/upload/v1590181336/amenities/PRIVATE_ROOMS.png"}},{"id":"PRIVATE_ROOMS","name":"Private Rooms","paid":true,"icons":{"size24":"https://images.loungebuddy.com/loungebuddy/image/upload/v1590181336/amenities/PRIVATE_ROOMS.png"}},{"id":"CHILDREN_ROOMS","name":"Children's Area","paid":false,"icons":{"size24":"https://images.loungebuddy.com/loungebuddy/image/upload/v1590181336/amenities/CHILDREN_ROOMS.png"}},{"id":"CONFERENCE_ROOMS_FREE","name":"Conference Rooms","paid":false,"icons":{"size24":"https://images.loungebuddy.com/loungebuddy/image/upload/v1590181336/amenities/CONFERENCE_ROOMS.png"}},{"id":"CONFERENCE_ROOMS","name":"Conference Rooms","paid":true,"icons":{"size24":"https://images.loungebuddy.com/loungebuddy/image/upload/v1590181336/amenities/CONFERENCE_ROOMS.png"}},{"id":"INTERNET_TERMINALS","name":"Internet Terminals","paid":false,"icons":{"size24":"https://images.loungebuddy.com/loungebuddy/image/upload/v1590181336/amenities/INTERNET_TERMINALS.png"}},{"id":"PRINTERS_FREE","name":"Printers & Copiers","paid":false,"icons":{"size24":"https://images.loungebuddy.com/loungebuddy/image/upload/v1590181336/amenities/PRINTERS.png"}},{"id":"PRINTERS","name":"Printers & Copiers","paid":true,"icons":{"size24":"https://images.loungebuddy.com/loungebuddy/image/upload/v1590181336/amenities/PRINTERS.png"}},{"id":"TELEPHONES","name":"Telephones","paid":false,"icons":{"size24":"https://images.loungebuddy.com/loungebuddy/image/upload/v1590181336/amenities/TELEPHONES.png"}},{"id":"SMOKING_ROOMS","name":"Smoking Area","paid":false,"icons":{"size24":"https://images.loungebuddy.com/loungebuddy/image/upload/v1590181336/amenities/SMOKING_ROOMS.png"}},{"id":"NON-SMOKING","name":"Non-Smoking","paid":false,"icons":{"size24":"https://images.loungebuddy.com/loungebuddy/image/upload/v1590181336/amenities/NON-SMOKING.png"}},{"id":"SHOE_SHINE","name":"Shoe Shine","paid":false,"icons":{"size24":"https://images.loungebuddy.com/loungebuddy/image/upload/v1590181336/amenities/SHOE_SHINE.png"}},{"id":"18_CARDHOLDER","name":"18+ Cardholder","paid":false,"icons":{"size24":"https://images.loungebuddy.com/loungebuddy/image/upload/v1590181336/amenities/18_CARDHOLDER.png"}},{"id":"21_CARDHOLDER","name":"21+ Cardholder","paid":false,"icons":{"size24":"https://images.loungebuddy.com/loungebuddy/image/upload/v1590181336/amenities/21_CARDHOLDER.png"}},{"id":"GYM","name":"Gym","paid":true,"icons":{"size24":"https://images.loungebuddy.com/loungebuddy/image/upload/v1590181336/amenities/GYM.png"}},{"id":"GYM_FREE","name":"Gym","paid":false,"icons":{"size24":"https://images.loungebuddy.com/loungebuddy/image/upload/v1590181336/amenities/GYM.png"}},{"id":"CLOTHES_PRESS_FREE","name":"Clothes Press","paid":false,"icons":{"size24":"https://images.loungebuddy.com/loungebuddy/image/upload/v1590181336/amenities/CLOTHES_PRESS_FREE.png"}}],"reviews":[{"createdAt":"2019-02-07T23:38:25.592Z","visibilityRating":17.166666666666668,"rating":4,"member":{"profileIcon":"/images/lounges/avatar_2x_ij4mbe.png","name":"Fabiano","objectId":"xMEIJljHNs"},"type":{"parent":"6iypTOVK9Y","name":"review"},"content":"Very good lounge. Excellent wines and buffet. Comfortable seats.","parentId":"6iypTOVK9Y"},{"createdAt":"2018-11-04T08:58:06.829Z","visibilityRating":18.333333333333332,"rating":4,"member":{"profileIcon":"/images/lounges/avatar_2x_ij4mbe.png","name":"Laura","objectId":"8jgQUMrWiJ"},"type":{"parent":"6iypTOVK9Y","name":"review"},"content":"Really nice food options and spacious as well! A bit loud.","parentId":"6iypTOVK9Y"},{"createdAt":"2018-08-03T07:07:51.998Z","visibilityRating":19.416666666666668,"rating":4,"member":{"profileIcon":"/images/lounges/avatar_2x_ij4mbe.png","name":"Conrad","objectId":"eAYOVvaxE7"},"type":{"parent":"6iypTOVK9Y","name":"review"},"content":"Newly renovated and when I visited around 9:00 a.m. there were plenty of seats available throughout. Good breakfast and beverage options.","parentId":"6iypTOVK9Y"},{"createdAt":"2018-03-19T12:15:11.475Z","visibilityRating":21.083333333333332,"rating":4,"member":{"profileIcon":"/images/lounges/avatar_2x_ij4mbe.png","name":"KKP","objectId":"zXFZ5P0rih"},"type":{"parent":"6iypTOVK9Y","name":"review"},"content":"Worth about detour! Breakfast and lunch options were delicious and plenty. Was cool to watch the chef cook the meals. Staff was friendly. My only feedback would be more outlets and get new faucets.","parentId":"6iypTOVK9Y"}],"otherLounges":[],"capacity":null,"googleMapKey":"AIzaSyDaxxnWYwWefsgNxrzdkvEEexN5m7NSVew"}