{"status":200,"meta":{"description":"PAGSS Premium Lounge (International) at Francisco Bangoy International Airport (DVO), International Terminal. Learn more about the lounge: amenities, photos, review, opening hours, location."},"lounge":{"id":"AjkLWhQyp4","name":"PAGSS Premium Lounge (International)","terminal":"International Terminal","location":{"latitude":null,"longitude":null,"terminalDirections":"After Immigration and Security Checkpoint, 2nd Floor of the International Departure Area, opposite Gate 4."},"airside":"insideSecurity","loungeImage":"https://images.loungebuddy.com/loungebuddy/image/upload/t_keyart_mobile/v1459215296/DVO_PAGSS_Intl_Hero_kyri2s.jpg","hours":[[1400,1700],[1400,1700],[1400,1700],[1400,1700],[1400,1700],[1400,1700],[1400,2100]],"amenities":[{"id":"SNACKS","name":"Snacks","paid":false},{"id":"SPIRITS_LIQUOR","name":"Spirits & Liquor","paid":false},{"id":"BEER_WINE","name":"Beer & Wine","paid":false},{"id":"WIFI","name":"Wi-Fi","paid":false},{"id":"SHOWERS","name":"Showers","paid":true},{"id":"NEWSPAPERS","name":"Newspapers & Magazines","paid":false},{"id":"TV","name":"TVs","paid":false},{"id":"PRIVATE_ROOMS","name":"Private Rooms","paid":false},{"id":"INTERNET_TERMINALS","name":"Internet Terminals","paid":false},{"id":"NON-SMOKING","name":"Non-Smoking","paid":false}],"amenityGroups":null,"accessType":"WALKINS_ACCEPTED","tempClosed":"open","slugPath":"pagss-premium-lounge-international-international-terminal-AjkLWhQyp4","price":{"currency":"USD","price":15},"airport":{"id":"hG8hbWT2oe","IATA":"DVO","name":"Francisco Bangoy International Airport","location":{"latitude":7.130207,"longitude":125.645261,"description":"Davao City, Philippines","radius":200,"city":"Davao","countryCode":"PH","countryName":"Philippines"},"timeZone":"Asia/Manila","imageURL":"https://images.loungebuddy.com/loungebuddy/image/upload/v1478119624/klaizx5sggj3dgmqaf73.jpg"},"images":["https://images.loungebuddy.com/loungebuddy/image/upload/t_keyart_mobile/v1459215296/DVO_PAGSS_Intl_Hero_kyri2s.jpg"],"description":"Your airport sanctuary awaits at the PAGSS Premium Lounge before departure. With a wide range of snacks and entrees, alcoholic beverages, newspapers and magazines, and complimentary fast Wi-Fi, guests can relax or work undisturbed in a calm and tranquil environment.","purchasable":false,"importantInformation":{"general":["Children under 8 years old are admitted free with an adult.","Shower facility available for an additional charge of PHP 100 - payable directly at the front desk.","Limit 2 guests per Lounge Key, Priority Pass, or Lounge Club cardholder."],"warning":[],"regulatory":["This lounge is only accessible for departing international passengers."],"hasContent":true},"fullImages":["https://images.loungebuddy.com/loungebuddy/image/upload/c_fit,h_2000,w_2000/c5cqweof0qq2mnflwdyw.jpg","https://images.loungebuddy.com/loungebuddy/image/upload/c_fit,h_2000,w_2000/qla9p8wcqhfycj7fzfzr.jpg","https://images.loungebuddy.com/loungebuddy/image/upload/c_fit,h_2000,w_2000/xe2netpnwgwjlhs1gopx.jpg","https://images.loungebuddy.com/loungebuddy/image/upload/c_fit,h_2000,w_2000/e5gsadhod2htociotnf2.jpg","https://images.loungebuddy.com/loungebuddy/image/upload/c_fit,h_2000,w_2000/j3ymxuvgwa9hmwdrzzgk.jpg","https://images.loungebuddy.com/loungebuddy/image/upload/c_fit,h_2000,w_2000/lpc9d1q4ac3hyxifnjz2.jpg","https://images.loungebuddy.com/loungebuddy/image/upload/c_fit,h_2000,w_2000/hym24t1zo7ddm2pbn0nk.jpg","https://images.loungebuddy.com/loungebuddy/image/upload/c_fit,h_2000,w_2000/hxhhhlh5nylhniwazs26.jpg","https://images.loungebuddy.com/loungebuddy/image/upload/c_fit,h_2000,w_2000/qdgeciwmhwmk7qjtemz5.jpg","https://images.loungebuddy.com/loungebuddy/image/upload/c_fit,h_2000,w_2000/nb3mheh9qaf0l7qfejgd.jpg","https://images.loungebuddy.com/loungebuddy/image/upload/c_fit,h_2000,w_2000/qcpuagfpbm9ubgw1wald.jpg","https://images.loungebuddy.com/loungebuddy/image/upload/c_fit,h_2000,w_2000/a9uuvltysapbyhbcvn4u.jpg","https://images.loungebuddy.com/loungebuddy/image/upload/c_fit,h_2000,w_2000/ii8gx9b69hstmjsi9yoj.jpg","https://images.loungebuddy.com/loungebuddy/image/upload/c_fit,h_2000,w_2000/pcxkforplbg8ujbovl03.jpg","https://images.loungebuddy.com/loungebuddy/image/upload/c_fit,h_2000,w_2000/ntfeusuappeqf5cw4qkb.jpg","https://images.loungebuddy.com/loungebuddy/image/upload/c_fit,h_2000,w_2000/gtt2pagzupqx68wheafn.jpg","https://images.loungebuddy.com/loungebuddy/image/upload/c_fit,h_2000,w_2000/k5kockzw5uogbybltsjb.jpg","https://images.loungebuddy.com/loungebuddy/image/upload/c_fit,h_2000,w_2000/ghhpnsgwnwk5s9hhe1bz.jpg","https://images.loungebuddy.com/loungebuddy/image/upload/c_fit,h_2000,w_2000/cruyefe3f3vmvrlesmdb.jpg","https://images.loungebuddy.com/loungebuddy/image/upload/c_fit,h_2000,w_2000/o11rvu5tcjuf483ygkcd.jpg","https://images.loungebuddy.com/loungebuddy/image/upload/c_fit,h_2000,w_2000/d5vuqpnnybtdnnzfnksy.jpg","https://images.loungebuddy.com/loungebuddy/image/upload/c_fit,h_2000,w_2000/jhnrfigedoxujpgm7klm.jpg","https://images.loungebuddy.com/loungebuddy/image/upload/c_fit,h_2000,w_2000/xhgafcrscclh3rflpnob.jpg","https://images.loungebuddy.com/loungebuddy/image/upload/c_fit,h_2000,w_2000/tmrej8hheml6sos8c95u.jpg","https://images.loungebuddy.com/loungebuddy/image/upload/c_fit,h_2000,w_2000/teaky8editphi6iow6sa.jpg","https://images.loungebuddy.com/loungebuddy/image/upload/c_fit,h_2000,w_2000/pijwlxcppu1ts5dgidl0.jpg","https://images.loungebuddy.com/loungebuddy/image/upload/c_fit,h_2000,w_2000/rrtbfhbcsvshvntm7nht.jpg","https://images.loungebuddy.com/loungebuddy/image/upload/c_fit,h_2000,w_2000/kn7x0pe6040sd1zccb7l.jpg"],"bookingLoungeId":"LB_DVO_PAGSS_INTERNATIONAL"},"allAmenities":[{"id":"PREMIUM_FOOD_FREE","name":"Premium Food","paid":false,"icons":{"size24":"https://images.loungebuddy.com/loungebuddy/image/upload/v1590181336/amenities/PREMIUM_FOOD.png"}},{"id":"PREMIUM_FOOD","name":"Premium Food","paid":true,"icons":{"size24":"https://images.loungebuddy.com/loungebuddy/image/upload/v1590181336/amenities/PREMIUM_FOOD.png"}},{"id":"SNACKS_FREE","name":"Snacks","paid":false,"icons":{"size24":"https://images.loungebuddy.com/loungebuddy/image/upload/v1590181336/amenities/SNACKS_FREE.png"}},{"id":"SPIRITS_LIQUOR_FREE","name":"Spirits & Liquor","paid":false,"icons":{"size24":"https://images.loungebuddy.com/loungebuddy/image/upload/v1590181336/amenities/SPIRITS_LIQUOR.png"}},{"id":"SPIRITS_LIQUOR","name":"Spirits & Liquor","paid":true,"icons":{"size24":"https://images.loungebuddy.com/loungebuddy/image/upload/v1590181336/amenities/SPIRITS_LIQUOR.png"}},{"id":"BEER_WINE_FREE","name":"Beer & Wine","paid":false,"icons":{"size24":"https://images.loungebuddy.com/loungebuddy/image/upload/v1590181336/amenities/BEER_WINE.png"}},{"id":"BEER_WINE","name":"Beer & Wine","paid":true,"icons":{"size24":"https://images.loungebuddy.com/loungebuddy/image/upload/v1590181336/amenities/BEER_WINE.png"}},{"id":"WIFI_FREE","name":"Wi-Fi","paid":false,"icons":{"size24":"https://images.loungebuddy.com/loungebuddy/image/upload/v1590181336/amenities/WIFI.png"}},{"id":"WIFI","name":"Wi-Fi","paid":true,"icons":{"size24":"https://images.loungebuddy.com/loungebuddy/image/upload/v1590181336/amenities/WIFI.png"}},{"id":"SHOWERS_FREE","name":"Showers","paid":false,"icons":{"size24":"https://images.loungebuddy.com/loungebuddy/image/upload/v1590181336/amenities/SHOWERS.png"}},{"id":"SHOWERS","name":"Showers","paid":true,"icons":{"size24":"https://images.loungebuddy.com/loungebuddy/image/upload/v1590181336/amenities/SHOWERS.png"}},{"id":"SPA_FREE","name":"Spa Services","paid":false,"icons":{"size24":"https://images.loungebuddy.com/loungebuddy/image/upload/v1590181336/amenities/SPA.png"}},{"id":"SPA","name":"Spa Services","paid":true,"icons":{"size24":"https://images.loungebuddy.com/loungebuddy/image/upload/v1590181336/amenities/SPA.png"}},{"id":"FLIGHT_MONITORS","name":"Flight Monitors","paid":false,"icons":{"size24":"https://images.loungebuddy.com/loungebuddy/image/upload/v1590181336/amenities/FLIGHT_MONITORS.png"}},{"id":"NEWSPAPERS","name":"Newspapers & Magazines","paid":false,"icons":{"size24":"https://images.loungebuddy.com/loungebuddy/image/upload/v1590181336/amenities/NEWSPAPERS.png"}},{"id":"TV","name":"TVs","paid":false,"icons":{"size24":"https://images.loungebuddy.com/loungebuddy/image/upload/v1590181336/amenities/TV.png"}},{"id":"PRIVATE_ROOMS_FREE","name":"Private Rooms","paid":false,"icons":{"size24":"https://images.loungebuddy.com/loungebuddy/image/upload/v1590181336/amenities/PRIVATE_ROOMS.png"}},{"id":"PRIVATE_ROOMS","name":"Private Rooms","paid":true,"icons":{"size24":"https://images.loungebuddy.com/loungebuddy/image/upload/v1590181336/amenities/PRIVATE_ROOMS.png"}},{"id":"CHILDREN_ROOMS","name":"Children's Area","paid":false,"icons":{"size24":"https://images.loungebuddy.com/loungebuddy/image/upload/v1590181336/amenities/CHILDREN_ROOMS.png"}},{"id":"CONFERENCE_ROOMS_FREE","name":"Conference Rooms","paid":false,"icons":{"size24":"https://images.loungebuddy.com/loungebuddy/image/upload/v1590181336/amenities/CONFERENCE_ROOMS.png"}},{"id":"CONFERENCE_ROOMS","name":"Conference Rooms","paid":true,"icons":{"size24":"https://images.loungebuddy.com/loungebuddy/image/upload/v1590181336/amenities/CONFERENCE_ROOMS.png"}},{"id":"INTERNET_TERMINALS","name":"Internet Terminals","paid":false,"icons":{"size24":"https://images.loungebuddy.com/loungebuddy/image/upload/v1590181336/amenities/INTERNET_TERMINALS.png"}},{"id":"PRINTERS_FREE","name":"Printers & Copiers","paid":false,"icons":{"size24":"https://images.loungebuddy.com/loungebuddy/image/upload/v1590181336/amenities/PRINTERS.png"}},{"id":"PRINTERS","name":"Printers & Copiers","paid":true,"icons":{"size24":"https://images.loungebuddy.com/loungebuddy/image/upload/v1590181336/amenities/PRINTERS.png"}},{"id":"TELEPHONES","name":"Telephones","paid":false,"icons":{"size24":"https://images.loungebuddy.com/loungebuddy/image/upload/v1590181336/amenities/TELEPHONES.png"}},{"id":"SMOKING_ROOMS","name":"Smoking Area","paid":false,"icons":{"size24":"https://images.loungebuddy.com/loungebuddy/image/upload/v1590181336/amenities/SMOKING_ROOMS.png"}},{"id":"NON-SMOKING","name":"Non-Smoking","paid":false,"icons":{"size24":"https://images.loungebuddy.com/loungebuddy/image/upload/v1590181336/amenities/NON-SMOKING.png"}},{"id":"SHOE_SHINE","name":"Shoe Shine","paid":false,"icons":{"size24":"https://images.loungebuddy.com/loungebuddy/image/upload/v1590181336/amenities/SHOE_SHINE.png"}},{"id":"18_CARDHOLDER","name":"18+ Cardholder","paid":false,"icons":{"size24":"https://images.loungebuddy.com/loungebuddy/image/upload/v1590181336/amenities/18_CARDHOLDER.png"}},{"id":"21_CARDHOLDER","name":"21+ Cardholder","paid":false,"icons":{"size24":"https://images.loungebuddy.com/loungebuddy/image/upload/v1590181336/amenities/21_CARDHOLDER.png"}},{"id":"GYM","name":"Gym","paid":true,"icons":{"size24":"https://images.loungebuddy.com/loungebuddy/image/upload/v1590181336/amenities/GYM.png"}},{"id":"GYM_FREE","name":"Gym","paid":false,"icons":{"size24":"https://images.loungebuddy.com/loungebuddy/image/upload/v1590181336/amenities/GYM.png"}},{"id":"CLOTHES_PRESS_FREE","name":"Clothes Press","paid":false,"icons":{"size24":"https://images.loungebuddy.com/loungebuddy/image/upload/v1590181336/amenities/CLOTHES_PRESS_FREE.png"}}],"reviews":[],"otherLounges":[],"capacity":null,"googleMapKey":"AIzaSyDaxxnWYwWefsgNxrzdkvEEexN5m7NSVew"}